kairyou/__init__.py
kairyou/exceptions.py
kairyou/indexer.py
kairyou/kairyou.py
kairyou/katakana_util.py
kairyou/types.py
kairyou/util.py
kairyou/words.py
kairyou-1.40.dist-info/LICENSE.md
kairyou-1.40.dist-info/METADATA
kairyou-1.40.dist-info/WHEEL
kairyou-1.40.dist-info/top_level.txt
kairyou-1.40.dist-info/RECORD
