Metadata-Version: 2.1
Name: kairyou
Version: 1.40
Summary: Quickly preprocesses Japanese text using NLP/NER from SpaCy for Japanese translation or other NLP tasks.
Author-email: Bikatr7 <Tetralon07@gmail.com>
Project-URL: Homepage, https://github.com/Bikatr7/Kairyou
Project-URL: Issues, https://github.com/Bikatr7/Kairyou/issues
Classifier: Programming Language :: Python :: 3.8
Classifier: License :: OSI Approved :: GNU General Public License v3 (GPLv3)
Classifier: Operating System :: OS Independent
Requires-Python: >=3.8
License-File: LICENSE.md
Requires-Dist: spacy <3.8.0,>=3.7.0
